thingsboard/__init__.py
thingsboard/endpoint/__init__.py
thingsboard/endpoint/endpoint.py
thingsboard/endpoint/properties_endpoint_configuration.py
thingsboard/endpoint/topicuuid.py
thingsboard/endpoint/version.py
thingsboard/endpoint/attribute/__init__.py
thingsboard/endpoint/attribute/attribute.py
thingsboard/endpoint/attribute/constraint.py
thingsboard/endpoint/attribute/decorator.py
thingsboard/endpoint/attribute/type.py
thingsboard/endpoint/connector/__init__.py
thingsboard/endpoint/connector/model_to_cloud.py
thingsboard/endpoint/exception/__init__.py
thingsboard/endpoint/exception/invalid_attribute_exception.py
thingsboard/endpoint/exception/invalid_attribute_type_exception.py
thingsboard/endpoint/exception/invalid_property_exception.py
thingsboard/endpoint/exception/modification_exception.py
thingsboard/endpoint/factory/__init__.py
thingsboard/endpoint/factory/xml.py
thingsboard/endpoint/interface/__init__.py
thingsboard/endpoint/interface/attribute_container.py
thingsboard/endpoint/interface/attribute_listener.py
thingsboard/endpoint/interface/message_format.py
thingsboard/endpoint/interface/named_item.py
thingsboard/endpoint/interface/node_container.py
thingsboard/endpoint/interface/object_container.py
thingsboard/endpoint/interface/unique_identifiable.py
thingsboard/endpoint/interface/uuid.py
thingsboard/endpoint/message_format/__init__.py
thingsboard/endpoint/message_format/factory.py
thingsboard/endpoint/message_format/json_format.py
thingsboard/endpoint/message_format/jsonzip_format.py
thingsboard/endpoint/message_format/thingsboard_format.py
thingsboard/endpoint/mqtt/__init__.py
thingsboard/endpoint/mqtt/client.py
thingsboard/endpoint/mqtt/pending_update.py
thingsboard/endpoint/mqtt/persistence.py
thingsboard/endpoint/node/__init__.py
thingsboard/endpoint/node/node.py
thingsboard/endpoint/object/__init__.py
thingsboard/endpoint/object/object.py
thingsboard/endpoint/runtime/__init__.py
thingsboard/endpoint/runtime/node.py
thingsboard_endpoint-0.2.0.dist-info/licenses/LICENSE
thingsboard_endpoint-0.2.0.dist-info/METADATA
thingsboard_endpoint-0.2.0.dist-info/WHEEL
thingsboard_endpoint-0.2.0.dist-info/top_level.txt
thingsboard_endpoint-0.2.0.dist-info/RECORD
