Metadata-Version: 2.4
Name: thingsboard-endpoint
Version: 0.2.0
Summary: ThingsBoard endpoint package
Home-page: https://gitlab.com/things-board
Author: HES-SO Valais, School of Engineering, Sion
Author-email: thomas.sterren@hes-so.ch
License-Expression: MIT
Project-URL: Bug Tracker, https://gitlab.com/things-board/thingsboard-endpoint/-/issues
Project-URL: Source Code, https://gitlab.com/things-board/thingsboard-endpoint
Project-URL: Documentation, https://gitlab.com/things-board/thingsboard-endpoint#thingsboard-endpoint
Keywords: ThingsBoard endpoint library
Classifier: Development Status :: 3 - Alpha
Classifier: Intended Audience :: Developers
Classifier: Intended Audience :: Education
Classifier: Intended Audience :: Science/Research
Classifier: Intended Audience :: Information Technology
Classifier: Topic :: Software Development :: Libraries :: Python Modules
Classifier: Programming Language :: Python :: 3.12
Classifier: Programming Language :: Python :: 3.13
Classifier: Operating System :: OS Independent
Requires-Python: >=3.9
License-File: LICENSE
Requires-Dist: thingsboard-common<1.0.0
Requires-Dist: configobj<6.0.0,>=5.0.9
Dynamic: author
Dynamic: author-email
Dynamic: classifier
Dynamic: home-page
Dynamic: keywords
Dynamic: license-file
Dynamic: project-url
Dynamic: requires-dist
Dynamic: summary
